gemurl.py
gemurl-1.1.0.dist-info/METADATA
gemurl-1.1.0.dist-info/WHEEL
gemurl-1.1.0.dist-info/entry_points.txt
gemurl-1.1.0.dist-info/top_level.txt
gemurl-1.1.0.dist-info/RECORD
