Metadata-Version: 2.1
Name: gemurl
Version: 1.1.0
Summary: "A library for normalizing gemini:// URLs"
Home-page: https://github.com/raek/gemurl
Author: Rasmus Bondesson
Author-email: raek@raek.se
License: MIT
Classifier: Development Status :: 4 - Beta
Classifier: Programming Language :: Python :: 3
Classifier: License :: OSI Approved :: MIT License
Classifier: Topic :: Internet
Classifier: Topic :: Utilities
Requires-Python: >=3.6
Provides-Extra: test
Requires-Dist: flake8 ; extra == 'test'
Requires-Dist: pytest ; extra == 'test'
